uvoxen/__init__.py
uvoxen/__main__.py
uvoxen/defs.py
uvoxen/expand_tox_vars.py
uvoxen/parse.py
uvoxen/util.py
uvoxen/run/__init__.py
uvoxen/run/base.py
uvoxen/run/req.py
uvoxen/run/tox.py
uvoxen/run/uv.py
uvoxen-0.2.3.dist-info/METADATA
uvoxen-0.2.3.dist-info/WHEEL
uvoxen-0.2.3.dist-info/entry_points.txt
uvoxen-0.2.3.dist-info/licenses/LICENSES/BSD-2-Clause.txt
uvoxen-0.2.3.dist-info/RECORD
