Metadata-Version: 2.4
Name: uvoxen
Version: 0.2.3
Summary: Generate test configuration files and run tests
Project-URL: Homepage, https://devel.ringlet.net/devel/uvoxen/
Project-URL: Changes, https://devel.ringlet.net/devel/uvoxen/changes/
Project-URL: Issue Tracker, https://gitlab.com/ppentchev/uvoxen/-/issues
Project-URL: Source Code, https://gitlab.com/ppentchev/uvoxen
Author-email: Peter Pentchev <roam@ringlet.net>
License-Expression: BSD-2-Clause
License-File: LICENSES/BSD-2-Clause.txt
Classifier: Development Status :: 5 - Production/Stable
Classifier: Intended Audience :: Developers
Classifier: Operating System :: OS Independent
Classifier: Programming Language :: Python
Classifier: Programming Language :: Python :: 3
Classifier: Programming Language :: Python :: 3 :: Only
Classifier: Programming Language :: Python :: 3.11
Classifier: Programming Language :: Python :: 3.12
Classifier: Programming Language :: Python :: 3.13
Classifier: Programming Language :: Python :: 3.14
Classifier: Topic :: Software Development :: Libraries
Classifier: Topic :: Software Development :: Libraries :: Python Modules
Classifier: Topic :: Software Development :: Testing
Classifier: Topic :: Software Development :: Testing :: Unit
Classifier: Typing :: Typed
Requires-Python: >=3.11
Requires-Dist: cappa<0.31,>=0.27.3
Requires-Dist: media-type-version<0.3,>=0.1
Requires-Dist: pyparsing<4,>=3.1
Requires-Dist: typedload<3,>=2.22
Requires-Dist: uv<0.10,>=0.5
